dffMy.sv
module dffMy (
    input logic clk,
    input logic reset,
    input logic d_in,
    output reg q_out
);

    always_ff @(posedge clk or posedge reset) begin
        if (reset)
            q_out <= 1'b0;
        else
            q_out <= d_in;
    end

endmodule

sumAcc.sv
module sumAcc #(
    parameter WIDTH = 8,
              N = 4,
              ACC_WIDTH  = 2 * WIDTH + $clog2(N),
              MODE = 0 // 0 - unsigned, 1 - signed
) (
  input logic  [2*WIDTH-1:0] in_x,
  input logic  [ACC_WIDTH-1:0] in_accum,
  output logic  [ACC_WIDTH-1:0] out
);

//Размерность до ACC_WIDTH вручную
logic [ACC_WIDTH-1:0] in_y;

//Размерность + Выходы
generate
    if (MODE == 1) begin
        //assign in_y = {{(ACC_WIDTH - 2*WIDTH){in_accum[2*WIDTH-1]}}, in_accum};
        assign out = $signed(in_x) + $signed(in_y);
        end 
    else begin
          //assign in_y = {{(ACC_WIDTH - 2*WIDTH){1'b0}}, in_accum};
          assign out = in_x + in_y;
          end
endgenerate

endmodule

regAcc.sv
module regAcc #(
    parameter   WIDTH = 8,
                N = 4,
                ACC_WIDTH  = 2 * WIDTH + $clog2(N)    
    ) 
(
    input logic [ACC_WIDTH-1:0] d_in,
    input logic reset,
    input logic clk,
    output reg [ACC_WIDTH-1:0] q_out
);

always @(posedge clk or posedge reset) begin
    if (reset)
    begin
        q_out <= {WIDTH{1'b0}};
    end else begin
        q_out <= d_in;
    end
end


endmodule

mult.sv
module mult #(
    parameter WIDTH = 8,
    parameter MODE = 0 // 0 - unsigned, 1 - signed
) (
    input logic [WIDTH-1:0] in_x,
    input logic [WIDTH-1:0] in_y,
    output logic [WIDTH*2-1:0] out
);

generate
    if (MODE == 1)
        assign out = $signed(in_x) * $signed(in_y);
    else
        assign out = in_x * in_y;
endgenerate

endmodule

regEnable.sv
module regEnable #(
    parameter WIDTH = 8) (
    input logic [WIDTH-1:0] d_in,
    input logic clk,
    input logic enable,
    input logic reset,
    output reg [WIDTH-1:0] q_out
);

always @(posedge clk or posedge reset) begin
    if (reset)
        q_out <= {WIDTH{1'b0}};
    else if (enable)
        q_out <= d_in;
end

endmodule

regX.sv
module regX #(
    parameter WIDTH = 8
    ) 
    (
    input logic [WIDTH-1:0] d_in,
    input logic clk,
    input logic reset,
    output reg [WIDTH-1:0] q_out
);

always_ff @(posedge clk or posedge reset) begin
    if (reset)
    begin
        q_out <= {WIDTH{1'b0}};
    end else begin
        q_out <= d_in;
    end
end

endmodule

regChain.sv
module regChain #(
    parameter WIDTH = 8,
    parameter N = 4 
)(
    input logic clk,
    input logic reset,
    input logic [WIDTH-1:0] d_in,
    output logic [WIDTH-1:0] q_out
);

    //Провода для соединения регистров в genvar
    //Ширина width-1:0 по N штук
    logic [WIDTH-1:0] chained [0:N];

    assign chained[0] = d_in;

    genvar i;
    generate 
        for (i = 0; i < N; i = i + 1) begin : gen_reg
            regX #(.WIDTH(WIDTH)) u_reg (
                .d_in(chained[i]),
                .clk(clk),
                .reset(reset),
                .q_out(chained[i+1])
            );
        end
    endgenerate
    
    assign q_out = chained[N];

endmodule

andMux.sv
module andMux #(parameter WIDTH = 8) (
    input logic [WIDTH-1:0] in,
    input logic pass,
    output logic [WIDTH-1:0] out
);

assign out = pass ? in : {WIDTH{1'b0}};

endmodule

notA.sv
module notA(
    input logic a,
    output logic out
);

assign out = ~a;

endmodule

orMux.sv
module orMux #(parameter WIDTH = 8) (
    input logic [WIDTH-1:0] in_x,
    input logic [WIDTH-1:0] in_y,
    output logic [WIDTH-1:0] out
);

assign out = in_x | in_y;

endmodule

processingElement.sv
module processingElement #(
    parameter   WIDTH = 8,
                N = 4,
                ACC_WIDTH  = 2 * WIDTH + $clog2(N),
				MODE = 0,
                ID = 0
) (
    input logic clk, 
    input logic reset,
    input logic alpha, 
    input logic beta,
    input logic [WIDTH-1:0] a,
    input logic [WIDTH-1:0] b,
    input logic [ACC_WIDTH-1:0] c,

    output logic [WIDTH-1:0] a_j2,
    output logic [WIDTH-1:0] b_j2,
    output logic alpha_j1,
    output logic beta_j1,
    output logic [ACC_WIDTH-1:0] c_j1
);

//Цепочка регистров R1
//Рассчитываем количество регистров в R1 исходя из порядкового номера
localparam N1 = (ID < ((N + 1) / 2)) ? (N + 1) : (N - 1);
regChain #(.WIDTH(WIDTH), .N(N1)) r1 (
    .clk(clk),
    .reset(reset),
    .d_in(b),
    .q_out(b_j2)
);

logic [WIDTH-1:0] and1_or1;

andMux #(.WIDTH(WIDTH)) and1 (
    .in(b),
    .pass(alpha),
    .out(and1_or1)
);

logic [WIDTH-1:0] or1_r2;
logic [WIDTH-1:0] and2_or1;

orMux #(.WIDTH(WIDTH)) or1 (
    .in_x(and1_or1),
    .in_y(and2_or1),
    .out(or1_r2)
);

logic [WIDTH-1:0] reg2_1_out;

//Первый регистр группы R2 отдельно
//Нужен выход с него в умножитель
regX #(.WIDTH(WIDTH)) r2_1 (
    .clk(clk),
    .reset(reset),
    .d_in(or1_r2),
    .q_out(reg2_1_out)
);

logic [WIDTH-1:0] r2_and2;

regChain #(.WIDTH(WIDTH), .N(N-1)) r2 (
    .clk(clk),
    .reset(reset),
    .d_in(reg2_1_out),
    .q_out(r2_and2)
);

logic not1_and2;

notA n1 (.a(alpha), .out(not1_and2));

andMux #(.WIDTH(WIDTH)) and2 (
    .in(r2_and2),
    .pass(not1_and2),
    .out(and2_or1)
);

//Линия задержек для Aj из двух регистров
//Попробую тоже в regChain запихать хотя мб лучше раздельно
regChain #(.WIDTH(WIDTH), .N(2)) r34 (
    .reset(reset),
    .clk(clk),
    .d_in(a),
    .q_out(a_j2)
);

logic and3_reg5;

logic [WIDTH-1:0] reg5_mult;
//Тут не от clk а от and с clk
//and(and3_reg5, clk, beta) заменено на enable
regEnable #(.WIDTH(WIDTH)) r5 (
    .reset(reset),
    .clk(clk),
    .enable(beta),
    .d_in(a),
    .q_out(reg5_mult)
);

logic [2*WIDTH-1:0] mult_to_sum;

mult #(.WIDTH(WIDTH), .MODE(MODE)) m1 (
    .in_x(reg5_mult),
    .in_y(reg2_1_out),
    .out(mult_to_sum)
);

logic [ACC_WIDTH-1:0] r6_sum;

regAcc #(.WIDTH(WIDTH), .N(N), .ACC_WIDTH(ACC_WIDTH)) r6 (
    .clk(clk),
    .d_in(c),
    .q_out(r6_sum)
);

sumAcc #(.WIDTH(WIDTH), .N(N), .ACC_WIDTH(ACC_WIDTH), .MODE(MODE)) s1 (
    .in_x(mult_to_sum),
    .in_accum(r6_sum),
    .out(c_j1)
);

//Не хочет создавать просто dff
dffMy d1(
    .clk(clk),
    .reset(reset),
    .d_in(alpha),
    .q_out(alpha_j1)
);

dffMy d2(
    .clk(clk),
    .reset(reset),
    .d_in(beta),
	 .q_out(beta_j1)
);

endmodule

tb_pe.sv
`timescale 1ns/1ps

module tb_pe;
    localparam WIDTH = 8;
    localparam N = 4;
    localparam ACC_WIDTH = 2 * WIDTH + $clog2(N); // 18 бит
    localparam MODE = 0;  // 0 = unsigned, 1 = signed
    localparam ID = 0;

    logic                       clk;
    logic                       reset;
    logic                       alpha;
    logic                       beta;
    logic [WIDTH-1:0]           a;
    logic [WIDTH-1:0]           b;
    logic [ACC_WIDTH-1:0]       c;

    logic [WIDTH-1:0]           a_j2;
    logic [WIDTH-1:0]           b_j2;
    logic                       alpha_j1;
    logic                       beta_j1;
    logic [ACC_WIDTH-1:0]       c_j1;

    processingElement #(
        .WIDTH(WIDTH),
        .N(N),
        .ACC_WIDTH(ACC_WIDTH),
        .MODE(MODE),
        .ID(ID)
    ) pe (
        .clk      (clk),
        .reset    (reset),
        .alpha    (alpha),
        .beta     (beta),
        .a        (a),
        .b        (b),
        .c        (c),
        .a_j2     (a_j2),
        .b_j2     (b_j2),
        .alpha_j1 (alpha_j1),
        .beta_j1  (beta_j1),
        .c_j1     (c_j1)
    );

    initial begin
        clk = 0;
        forever #10 clk = ~clk;
    end

    initial begin
        $display("PE TestBench start.");
        $display("Parameters: WIDTH=%0d, N=%0d, ACC_WIDTH=%0d, MODE=%0d, ID=%0d",
                 WIDTH, N, ACC_WIDTH, MODE, ID);

        reset = 1;
        alpha = 0; 
        beta = 0; 
        a = 0; 
        b = 0;
        c = 0;
        #20 
        reset = 0;
        #100;
        
        $display("Loading B loop register.");
        #20;
        b<=8; 
        alpha<=1; 
        beta<=0;
        #20;
        b<=6; 
        alpha<=1; 
        beta<=0;
        #20;

        //Init + load new A and B with t=(1,1)
        $display("\n1. Инициализация + берём новые A и B с t=(1,1).");
        alpha <= 1;
        beta <= 1;
        a <= 8'd10;
        b <= 8'd5;
        c <= 18'd0;
        #20;
        $display("  Input: a=%0d, b=%0d, c=%0d | α=%b, β=%b", a, b, c, alpha, beta);
        $display("  Output: %0d * %0d + %0d = %0d", a, b, c, c_j1);
        assert(c_j1 == a * b + c);

        //Test t=(1,0), A is reused, B is loaded
        $display("\n2. Тест с  t=(1,0), A переиспользуем, B берём новую..");
        alpha <= 1; 
        beta <= 0;
        a <= 8'd20;  //Should not be in R5
        b <= 8'd3;
        c <= 18'd50; //Accumulated summ
        #20;
        $display("  Input: a=%0d (вместо него берём a=10), b=%0d, c=%0d | α=%b, β=%b", a, b, c, alpha, beta);
        $display("  Output: %0d * %0d + %0d = %0d", 10, b, c, c_j1);
        assert(c_j1 == 10 * b + c);

        //Cyclical B, new A is loaded. t = (0,1)
        $display("\n3. Берём новую А, B из конца кольца, t = (0,1)");
        alpha <= 0; 
        beta <= 1;
        a <= 8'd7;
        b <= 8'd1;  //Ignored, taking old
        c <= 18'd101;
        #20;
        $display("  Input: a=%0d, b=%0d (игнорируем, берём с кольца b = 8), c=%0d | α=%b, β=%b", a, b, c, alpha, beta);
        $display("  Output: %0d * %0d + %0d = %0d", a, 8, c, c_j1);
        assert(c_j1 == a * 8 + c);

        //Cyclical B + old A, t = (0,0)
        $display("\n4. Режим (α,β)=(0,0) — B из кольца и старое А");
        alpha <= 0; 
        beta <= 0;
        a <= 8'd99;  // Ignored
        b <= 8'd99;  // Ignored
        c <= 18'd200;
        #20;
        $display("  Input: a=%0d, b=%0d (оба игнорируем), c=%0d | α=%b, β=%b", a, b, c, alpha, beta);
        $display("  Output: %0d * %0d + %0d = %0d", 7, 6, c, c_j1);
        assert(c_j1 == 7 * 6 + c);

        #40;
        $display("\nFinished!");
        $finish;
    end

    initial begin
        $dumpfile("tb_pe_waveform.vcd");
        $dumpvars();
    end

endmodule

tb_pe_waveform.vcd
$date
	Mon Jun  1 16:01:20 2026
$end
$version
	Icarus Verilog
$end
$timescale
	1ps
$end
$scope module tb_pe $end
$var wire 18 ! c_j1 [17:0] $end
$var wire 1 " beta_j1 $end
$var wire 8 # b_j2 [7:0] $end
$var wire 1 $ alpha_j1 $end
$var wire 8 % a_j2 [7:0] $end
$var parameter 65 & ACC_WIDTH $end
$var parameter 32 ' ID $end
$var parameter 32 ( MODE $end
$var parameter 32 ) N $end
$var parameter 32 * WIDTH $end
$var reg 8 + a [7:0] $end
$var reg 1 , alpha $end
$var reg 8 - b [7:0] $end
$var reg 1 . beta $end
$var reg 18 / c [17:0] $end
$var reg 1 0 clk $end
$var reg 1 1 reset $end
$scope module pe $end
$var wire 8 2 a [7:0] $end
$var wire 1 , alpha $end
$var wire 8 3 b [7:0] $end
$var wire 1 . beta $end
$var wire 18 4 c [17:0] $end
$var wire 1 0 clk $end
$var wire 1 1 reset $end
$var wire 8 5 reg5_mult [7:0] $end
$var wire 8 6 reg2_1_out [7:0] $end
$var wire 18 7 r6_sum [17:0] $end
$var wire 8 8 r2_and2 [7:0] $end
$var wire 8 9 or1_r2 [7:0] $end
$var wire 1 : not1_and2 $end
$var wire 16 ; mult_to_sum [15:0] $end
$var wire 18 < c_j1 [17:0] $end
$var wire 1 " beta_j1 $end
$var wire 8 = b_j2 [7:0] $end
$var wire 8 > and2_or1 [7:0] $end
$var wire 8 ? and1_or1 [7:0] $end
$var wire 1 $ alpha_j1 $end
$var wire 8 @ a_j2 [7:0] $end
$var parameter 65 A ACC_WIDTH $end
$var parameter 32 B ID $end
$var parameter 32 C MODE $end
$var parameter 32 D N $end
$var parameter 33 E N1 $end
$var parameter 32 F WIDTH $end
$scope module and1 $end
$var wire 8 G in [7:0] $end
$var wire 1 , pass $end
$var wire 8 H out [7:0] $end
$var parameter 32 I WIDTH $end
$upscope $end
$scope module and2 $end
$var wire 1 : pass $end
$var wire 8 J out [7:0] $end
$var wire 8 K in [7:0] $end
$var parameter 32 L WIDTH $end
$upscope $end
$scope module d1 $end
$var wire 1 0 clk $end
$var wire 1 , d_in $end
$var wire 1 1 reset $end
$var reg 1 $ q_out $end
$upscope $end
$scope module d2 $end
$var wire 1 0 clk $end
$var wire 1 . d_in $end
$var wire 1 1 reset $end
$var reg 1 " q_out $end
$upscope $end
$scope module m1 $end
$var wire 16 M out [15:0] $end
$var wire 8 N in_y [7:0] $end
$var wire 8 O in_x [7:0] $end
$var parameter 32 P MODE $end
$var parameter 32 Q WIDTH $end
$scope begin genblk1 $end
$upscope $end
$upscope $end
$scope module n1 $end
$var wire 1 , a $end
$var wire 1 : out $end
$upscope $end
$scope module or1 $end
$var wire 8 R in_x [7:0] $end
$var wire 8 S in_y [7:0] $end
$var wire 8 T out [7:0] $end
$var parameter 32 U WIDTH $end
$upscope $end
$scope module r1 $end
$var wire 1 0 clk $end
$var wire 8 V d_in [7:0] $end
$var wire 8 W q_out [7:0] $end
$var wire 1 1 reset $end
$var parameter 33 X N $end
$var parameter 32 Y WIDTH $end
$scope begin gen_reg[0] $end
$var parameter 2 Z i $end
$scope module u_reg $end
$var wire 1 0 clk $end
$var wire 8 [ d_in [7:0] $end
$var wire 1 1 reset $end
$var parameter 32 \ WIDTH $end
$var reg 8 ] q_out [7:0] $end
$upscope $end
$upscope $end
$scope begin gen_reg[1] $end
$var parameter 2 ^ i $end
$scope module u_reg $end
$var wire 1 0 clk $end
$var wire 8 _ d_in [7:0] $end
$var wire 1 1 reset $end
$var parameter 32 ` WIDTH $end
$var reg 8 a q_out [7:0] $end
$upscope $end
$upscope $end
$scope begin gen_reg[2] $end
$var parameter 3 b i $end
$scope module u_reg $end
$var wire 1 0 clk $end
$var wire 8 c d_in [7:0] $end
$var wire 1 1 reset $end
$var parameter 32 d WIDTH $end
$var reg 8 e q_out [7:0] $end
$upscope $end
$upscope $end
$scope begin gen_reg[3] $end
$var parameter 3 f i $end
$scope module u_reg $end
$var wire 1 0 clk $end
$var wire 8 g d_in [7:0] $end
$var wire 1 1 reset $end
$var parameter 32 h WIDTH $end
$var reg 8 i q_out [7:0] $end
$upscope $end
$upscope $end
$scope begin gen_reg[4] $end
$var parameter 4 j i $end
$scope module u_reg $end
$var wire 1 0 clk $end
$var wire 8 k d_in [7:0] $end
$var wire 1 1 reset $end
$var parameter 32 l WIDTH $end
$var reg 8 m q_out [7:0] $end
$upscope $end
$upscope $end
$upscope $end
$scope module r2 $end
$var wire 1 0 clk $end
$var wire 8 n q_out [7:0] $end
$var wire 1 1 reset $end
$var wire 8 o d_in [7:0] $end
$var parameter 33 p N $end
$var parameter 32 q WIDTH $end
$scope begin gen_reg[0] $end
$var parameter 2 r i $end
$scope module u_reg $end
$var wire 1 0 clk $end
$var wire 8 s d_in [7:0] $end
$var wire 1 1 reset $end
$var parameter 32 t WIDTH $end
$var reg 8 u q_out [7:0] $end
$upscope $end
$upscope $end
$scope begin gen_reg[1] $end
$var parameter 2 v i $end
$scope module u_reg $end
$var wire 1 0 clk $end
$var wire 8 w d_in [7:0] $end
$var wire 1 1 reset $end
$var parameter 32 x WIDTH $end
$var reg 8 y q_out [7:0] $end
$upscope $end
$upscope $end
$scope begin gen_reg[2] $end
$var parameter 3 z i $end
$scope module u_reg $end
$var wire 1 0 clk $end
$var wire 8 { d_in [7:0] $end
$var wire 1 1 reset $end
$var parameter 32 | WIDTH $end
$var reg 8 } q_out [7:0] $end
$upscope $end
$upscope $end
$upscope $end
$scope module r2_1 $end
$var wire 1 0 clk $end
$var wire 8 ~ d_in [7:0] $end
$var wire 1 1 reset $end
$var parameter 32 !" WIDTH $end
$var reg 8 "" q_out [7:0] $end
$upscope $end
$scope module r34 $end
$var wire 1 0 clk $end
$var wire 8 #" d_in [7:0] $end
$var wire 8 $" q_out [7:0] $end
$var wire 1 1 reset $end
$var parameter 32 %" N $end
$var parameter 32 &" WIDTH $end
$scope begin gen_reg[0] $end
$var parameter 2 '" i $end
$scope module u_reg $end
$var wire 1 0 clk $end
$var wire 8 (" d_in [7:0] $end
$var wire 1 1 reset $end
$var parameter 32 )" WIDTH $end
$var reg 8 *" q_out [7:0] $end
$upscope $end
$upscope $end
$scope begin gen_reg[1] $end
$var parameter 2 +" i $end
$scope module u_reg $end
$var wire 1 0 clk $end
$var wire 8 ," d_in [7:0] $end
$var wire 1 1 reset $end
$var parameter 32 -" WIDTH $end
$var reg 8 ." q_out [7:0] $end
$upscope $end
$upscope $end
$upscope $end
$scope module r5 $end
$var wire 1 0 clk $end
$var wire 8 /" d_in [7:0] $end
$var wire 1 . enable $end
$var wire 1 1 reset $end
$var parameter 32 0" WIDTH $end
$var reg 8 1" q_out [7:0] $end
$upscope $end
$scope module r6 $end
$var wire 1 0 clk $end
$var wire 18 2" d_in [17:0] $end
$var wire 1 1 reset $end
$var parameter 65 3" ACC_WIDTH $end
$var parameter 32 4" N $end
$var parameter 32 5" WIDTH $end
$var reg 18 6" q_out [17:0] $end
$upscope $end
$scope module s1 $end
$var wire 18 7" in_accum [17:0] $end
$var wire 16 8" in_x [15:0] $end
$var wire 18 9" out [17:0] $end
$var wire 18 :" in_y [17:0] $end
$var parameter 65 ;" ACC_WIDTH $end
$var parameter 32 <" MODE $end
$var parameter 32 =" N $end
$var parameter 32 >" WIDTH $end
$scope begin genblk1 $end
$upscope $end
$upscope $end
$upscope $end
$upscope $end
$enddefinitions $end
$comment Show the parameter values. $end
$dumpall
b1000 >"
b100 ="
b0 <"
b10010 ;"
b1000 5"
b100 4"
b10010 3"
b1000 0"
b1000 -"
b1 +"
b1000 )"
b0 '"
b1000 &"
b10 %"
b1000 !"
b1000 |
b10 z
b1000 x
b1 v
b1000 t
b0 r
b1000 q
b11 p
b1000 l
b100 j
b1000 h
b11 f
b1000 d
b10 b
b1000 `
b1 ^
b1000 \
b0 Z
b1000 Y
b101 X
b1000 U
b1000 Q
b0 P
b1000 L
b1000 I
b1000 F
b101 E
b100 D
b0 C
b0 B
b10010 A
b1000 *
b100 )
b0 (
b0 '
b10010 &
$end
#0
$dumpvars
b0 :"
b0 9"
b0 8"
b0 7"
b0 6"
b0 2"
b0 1"
b0 /"
b0 ."
b0 ,"
b0 *"
b0 ("
b0 $"
b0 #"
b0 ""
b0 ~
b0 }
b0 {
b0 y
b0 w
b0 u
b0 s
b0 o
b0 n
b0 m
b0 k
b0 i
b0 g
b0 e
b0 c
b0 a
b0 _
b0 ]
b0 [
b0 W
b0 V
b0 T
b0 S
b0 R
b0 O
b0 N
b0 M
b0 K
b0 J
b0 H
b0 G
b0 @
b0 ?
b0 >
b0 =
b0 <
b0 ;
1:
b0 9
b0 8
b0 7
b0 6
b0 5
b0 4
b0 3
b0 2
11
00
b0 /
0.
b0 -
0,
b0 +
b0 %
0$
b0 #
0"
b0 !
$end
#10000
10
#20000
00
01
#30000
10
#40000
00
#50000
10
#60000
00
#70000
10
#80000
00
#90000
10
#100000
00
#110000
10
#120000
00
#130000
10
#140000
b1000 9
b1000 T
b1000 ~
b1000 ?
b1000 H
b1000 R
0:
1,
b1000 [
b1000 -
b1000 3
b1000 G
b1000 V
00
#150000
b1000 ]
b1000 _
b1000 s
b1000 6
b1000 N
b1000 o
b1000 ""
1$
10
#160000
b110 9
b110 T
b110 ~
b110 ?
b110 H
b110 R
b110 [
b110 -
b110 3
b110 G
b110 V
00
#170000
b1000 u
b1000 w
b110 s
b110 6
b110 N
b110 o
b110 ""
b1000 a
b1000 c
b110 ]
b110 _
10
#180000
b101 9
b101 T
b101 ~
b101 ?
b101 H
b101 R
b101 [
b101 -
b101 3
b101 G
b101 V
b1010 ("
b1010 +
b1010 2
b1010 #"
b1010 /"
1.
00
#190000
b110010 !
b110010 <
b110010 9"
b110010 :"
b110010 ;
b110010 M
b110010 8"
b101 ]
b101 _
b110 a
b110 c
b1000 e
b1000 g
b101 s
b101 6
b101 N
b101 o
b101 ""
b110 u
b110 w
b1000 y
b1000 {
b1010 *"
b1010 ,"
b1010 5
b1010 O
b1010 1"
1"
10
#200000
b11 9
b11 T
b11 ~
b11 ?
b11 H
b11 R
b110010 /
b110010 4
b110010 2"
b11 [
b11 -
b11 3
b11 G
b11 V
b10100 ("
b10100 +
b10100 2
b10100 #"
b10100 /"
0.
00
#210000
b11110 :"
b11110 ;
b11110 M
b11110 8"
0"
b1010000 !
b1010000 <
b1010000 9"
b110010 7
b110010 6"
b110010 7"
b1010 %
b1010 @
b1010 $"
b1010 ."
b10100 *"
b10100 ,"
b1000 8
b1000 K
b1000 n
b1000 }
b110 y
b110 {
b101 u
b101 w
b11 s
b11 6
b11 N
b11 o
b11 ""
b1000 i
b1000 k
b110 e
b110 g
b101 a
b101 c
b11 ]
b11 _
10
#220000
b1000 9
b1000 T
b1000 ~
b1000 >
b1000 J
b1000 S
b0 ?
b0 H
b0 R
1:
b1100101 /
b1100101 4
b1100101 2"
b1 [
b1 -
b1 3
b1 G
b1 V
b111 ("
b111 +
b111 2
b111 #"
b111 /"
1.
0,
00
#230000
b110 9
b110 T
b110 ~
b111000 :"
b110 >
b110 J
b110 S
b111000 ;
b111000 M
b111000 8"
b1 ]
b1 _
b11 a
b11 c
b101 e
b101 g
b110 i
b110 k
b1000 #
b1000 =
b1000 W
b1000 m
b1000 s
b1000 6
b1000 N
b1000 o
b1000 ""
b11 u
b11 w
b101 y
b101 {
b110 8
b110 K
b110 n
b110 }
b111 *"
b111 ,"
b10100 %
b10100 @
b10100 $"
b10100 ."
b111 5
b111 O
b111 1"
b10011101 !
b10011101 <
b10011101 9"
b1100101 7
b1100101 6"
b1100101 7"
0$
1"
10
#240000
b11001000 /
b11001000 4
b11001000 2"
b1100011 [
b1100011 -
b1100011 3
b1100011 G
b1100011 V
b1100011 ("
b1100011 +
b1100011 2
b1100011 #"
b1100011 /"
0.
00
#250000
b101 9
b101 T
b101 ~
b101010 :"
b101 >
b101 J
b101 S
b101010 ;
b101010 M
b101010 8"
0"
b11110010 !
b11110010 <
b11110010 9"
b11001000 7
b11001000 6"
b11001000 7"
b111 %
b111 @
b111 $"
b111 ."
b1100011 *"
b1100011 ,"
b101 8
b101 K
b101 n
b101 }
b11 y
b11 {
b1000 u
b1000 w
b110 s
b110 6
b110 N
b110 o
b110 ""
b110 #
b110 =
b110 W
b110 m
b101 i
b101 k
b11 e
b11 g
b1 a
b1 c
b1100011 ]
b1100011 _
10
#260000
00
#270000
b11101011 !
b11101011 <
b11101011 9"
b100011 :"
b11 9
b11 T
b11 ~
b100011 ;
b100011 M
b100011 8"
b11 >
b11 J
b11 S
b1100011 a
b1100011 c
b1 e
b1 g
b11 i
b11 k
b101 #
b101 =
b101 W
b101 m
b101 s
b101 6
b101 N
b101 o
b101 ""
b110 u
b110 w
b1000 y
b1000 {
b11 8
b11 K
b11 n
b11 }
b1100011 %
b1100011 @
b1100011 $"
b1100011 ."
10
#280000
00
#290000
b1000 9
b1000 T
b1000 ~
b11011101 !
b11011101 <
b11011101 9"
b10101 :"
b1000 >
b1000 J
b1000 S
b10101 ;
b10101 M
b10101 8"
b1000 8
b1000 K
b1000 n
b1000 }
b110 y
b110 {
b101 u
b101 w
b11 s
b11 6
b11 N
b11 o
b11 ""
b11 #
b11 =
b11 W
b11 m
b1 i
b1 k
b1100011 e
b1100011 g
10
