dffMy.sv
module dffMy (
    input logic clk,
    input logic reset,
    input logic d_in,
    output reg q_out
);

    always_ff @(posedge clk or posedge reset) begin
        if (reset)
            q_out <= 1'b0;
        else
            q_out <= d_in;
    end

endmodule

sumAcc.sv
module sumAcc #(
    parameter WIDTH = 8,
              N = 4,
              ACC_WIDTH  = 2 * WIDTH + $clog2(N),
              MODE = 0 // 0 - unsigned, 1 - signed
) (
  input logic  [2*WIDTH-1:0] in_x,
  input logic  [ACC_WIDTH-1:0] in_accum,
  output logic  [ACC_WIDTH-1:0] out
);

//Размерность до ACC_WIDTH вручную
logic [ACC_WIDTH-1:0] in_y;

//Размерность + Выходы
generate
    if (MODE == 1) begin
        //assign in_y = {{(ACC_WIDTH - 2*WIDTH){in_accum[2*WIDTH-1]}}, in_accum};
        assign out = $signed(in_x) + $signed(in_y);
        end 
    else begin
          //assign in_y = {{(ACC_WIDTH - 2*WIDTH){1'b0}}, in_accum};
          assign out = in_x + in_y;
          end
endgenerate

endmodule

regAcc.sv
module regAcc #(
    parameter   WIDTH = 8,
                N = 4,
                ACC_WIDTH  = 2 * WIDTH + $clog2(N)    
    ) 
(
    input logic [ACC_WIDTH-1:0] d_in,
    input logic clk,
    output reg [ACC_WIDTH-1:0] q_out
);

always @(posedge clk) begin
    q_out <= d_in;
end

endmodule

mult.sv
module mult #(
    parameter WIDTH = 8,
    parameter MODE = 0 // 0 - unsigned, 1 - signed
) (
    input logic [WIDTH-1:0] in_x,
    input logic [WIDTH-1:0] in_y,
    output logic [WIDTH*2-1:0] out
);

generate
    if (MODE == 1)
        assign out = $signed(in_x) * $signed(in_y);
    else
        assign out = in_x * in_y;
endgenerate

endmodule

regEnable.sv
module regEnable #(
    parameter WIDTH = 8) (
    input logic [WIDTH-1:0] d_in,
    input logic clk,
    input logic enable,
    input logic reset,
    output reg [WIDTH-1:0] q_out
);

always @(posedge clk or posedge reset) begin
    if (reset)
        q_out <= {WIDTH{1'b0}};
    else if (enable)
        q_out <= d_in;
end

endmodule

regX.sv
module regX #(
    parameter WIDTH = 8
    ) 
    (
    input logic [WIDTH-1:0] d_in,
    input logic clk,
    input logic reset,
    output reg [WIDTH-1:0] q_out
);

always @(posedge clk or posedge reset) begin
    if (reset)
    begin
        q_out <= {WIDTH{1'b0}};
    end else begin
        q_out <= d_in;
    end
end

endmodule

regChain.sv
module regChain #(
    parameter WIDTH = 8,
    parameter N = 4 
)(
    input logic clk,
    input logic reset,
    input logic [WIDTH-1:0] d_in,
    output logic [WIDTH-1:0] q_out
);

    //Провода для соединения регистров в genvar
    //Ширина width-1:0 по N штук
    logic [WIDTH-1:0] chained [0:N];

    assign chained[0] = d_in;

    genvar i;
    generate 
        for (i = 0; i < N; i = i + 1) begin : gen_reg
            regX #(.WIDTH(WIDTH)) u_reg (
                .d_in(chained[i]),
                .clk(clk),
                .reset(reset),
                .q_out(chained[i+1])
            );
        end
    endgenerate
    
    assign q_out = chained[N];

endmodule

andMux.sv
module andMux #(parameter WIDTH = 8) (
    input logic [WIDTH-1:0] in,
    input logic pass,
    output logic [WIDTH-1:0] out
);

assign out = pass ? in : {WIDTH{1'b0}};

endmodule

notA.sv
module notA(
    input logic a,
    output logic out
);

assign out = ~a;

endmodule

orMux.sv
module orMux #(parameter WIDTH = 8) (
    input logic [WIDTH-1:0] in_x,
    input logic [WIDTH-1:0] in_y,
    output logic [WIDTH-1:0] out
);

assign out = in_x | in_y;

endmodule

processingElement.sv
module processingElement #(
    parameter   WIDTH = 8,
                N = 4,
                ACC_WIDTH  = 2 * WIDTH + $clog2(N),
				MODE = 0,
                ID = 0
) (
    input logic clk, 
    input logic reset,
    input logic alpha, 
    input logic beta,
    input logic [WIDTH-1:0] a,
    input logic [WIDTH-1:0] b,
    input logic [ACC_WIDTH-1:0] c,

    output logic [WIDTH-1:0] a_j2,
    output logic [WIDTH-1:0] b_j2,
    output logic alpha_j1,
    output logic beta_j1,
    output logic [ACC_WIDTH-1:0] c_j1
);

//Цепочка регистров R1
//Рассчитываем количество регистров в R1 исходя из порядкового номера
localparam N1 = (ID < ((N + 1) / 2)) ? (N + 1) : (N - 1);
regChain #(.WIDTH(WIDTH), .N(N1)) r1 (
    .clk(clk),
    .reset(reset),
    .d_in(b),
    .q_out(b_j2)
);

logic [WIDTH-1:0] and1_or1;

andMux #(.WIDTH(WIDTH)) and1 (
    .in(b),
    .pass(alpha),
    .out(and1_or1)
);

logic [WIDTH-1:0] or1_r2;
logic [WIDTH-1:0] and2_or1;

orMux #(.WIDTH(WIDTH)) or1 (
    .in_x(and1_or1),
    .in_y(and2_or1),
    .out(or1_r2)
);

logic [WIDTH-1:0] reg2_1_out;

//Первый регистр группы R2 отдельно
//Нужен выход с него в умножитель
regX #(.WIDTH(WIDTH)) r2_1 (
    .clk(clk),
    .reset(reset),
    .d_in(or1_r2),
    .q_out(reg2_1_out)
);

logic [WIDTH-1:0] r2_and2;

regChain #(.WIDTH(WIDTH), .N(N-1)) r2 (
    .clk(clk),
    .reset(reset),
    .d_in(reg2_1_out),
    .q_out(r2_and2)
);

logic not1_and2;

notA n1 (.a(alpha), .out(not1_and2));

andMux #(.WIDTH(WIDTH)) and2 (
    .in(r2_and2),
    .pass(not1_and2),
    .out(and2_or1)
);

//Линия задержек для Aj из двух регистров
//Попробую тоже в regChain запихать хотя мб лучше раздельно
regChain #(.WIDTH(WIDTH), .N(2)) r34 (
    .reset(reset),
    .clk(clk),
    .d_in(a),
    .q_out(a_j2)
);

logic and3_reg5;

logic [WIDTH-1:0] reg5_mult;
//Тут не от clk а от and с clk
//and(and3_reg5, clk, beta) заменено на enable
regEnable #(.WIDTH(WIDTH)) r5 (
    .reset(reset),
    .clk(clk),
    .enable(beta),
    .d_in(a),
    .q_out(reg5_mult)
);

logic [2*WIDTH-1:0] mult_to_sum;

mult #(.WIDTH(WIDTH), .MODE(MODE)) m1 (
    .in_x(reg5_mult),
    .in_y(reg2_1_out),
    .out(mult_to_sum)
);

logic [ACC_WIDTH-1:0] r6_sum;

regAcc #(.WIDTH(WIDTH), .N(N), .ACC_WIDTH(ACC_WIDTH)) r6 (
    .clk(clk),
    .d_in(c),
    .q_out(r6_sum)
);

sumAcc #(.WIDTH(WIDTH), .N(N), .ACC_WIDTH(ACC_WIDTH), .MODE(MODE)) s1 (
    .in_x(mult_to_sum),
    .in_accum(r6_sum),
    .out(c_j1)
);

//Не хочет создавать просто dff
dffMy d1(
    .clk(clk),
    .reset(reset),
    .d_in(alpha),
    .q_out(alpha_j1)
);

dffMy d2(
    .clk(clk),
    .reset(reset),
    .d_in(beta),
	 .q_out(beta_j1)
);

endmodule

tb_pe.sv
`timescale 1ns/1ps

module tb_pe;
    localparam WIDTH = 8;
    localparam N = 2;
    localparam ACC_WIDTH = 2 * WIDTH + $clog2(N); // 18 бит
    localparam MODE = 0;  // 0 = unsigned, 1 = signed
    localparam ID = 0;

    logic                       clk;
    logic                       reset;
    logic                       alpha;
    logic                       beta;
    logic [WIDTH-1:0]           a;
    logic [WIDTH-1:0]           b;
    logic [ACC_WIDTH-1:0]       c;

    logic [WIDTH-1:0]           a_j2;
    logic [WIDTH-1:0]           b_j2;
    logic                       alpha_j1;
    logic                       beta_j1;
    logic [ACC_WIDTH-1:0]       c_j1;

    processingElement #(
        .WIDTH(WIDTH),
        .N(N),
        .ACC_WIDTH(ACC_WIDTH),
        .MODE(MODE),
        .ID(ID)
    ) pe (
        .clk      (clk),
        .reset    (reset),
        .alpha    (alpha),
        .beta     (beta),
        .a        (a),
        .b        (b),
        .c        (c),
        .a_j2     (a_j2),
        .b_j2     (b_j2),
        .alpha_j1 (alpha_j1),
        .beta_j1  (beta_j1),
        .c_j1     (c_j1)
    );

    initial begin
        clk = 0;
        forever #1 clk = ~clk;
    end

    initial begin
        $display("PE TestBench start.");
        $display("Parameters: WIDTH=%0d, N=%0d, ACC_WIDTH=%0d, MODE=%0d, ID=%0d",
                 WIDTH, N, ACC_WIDTH, MODE, ID);

        $display("=== FLUSH PHASE ===");
        reset = 1; #20; reset = 0; #10;

        // Прогон нулей для очистки конвейера
        alpha = 0; beta = 0; a = 0; b = 0; c = 0;
        for (integer i = 0; i < 10; i++) begin
            #10;
        end

        #2;
        reset = 0;
        #1;

        //Init + load new A and B with t=(1,1)
        $display("\n1. Init + load new A and B with t=(1,1).");
        alpha = 1; 
        beta = 1;
        a = 8'd10; 
        b = 8'd5; 
        c = 18'd0;
        #2;
        $display("  Input: a=%0d, b=%0d, c=%0d | α=%b, β=%b", a, b, c, alpha, beta);
        $display("  Output: a_j2=%0d, b_j2=%0d, c_j1=%0d", a_j2, b_j2, c_j1);

        //Test t=(1,0), A is reused, B is loaded
        $display("\n2. Test t=(1,0), A is reused, B is loaded.");
        alpha = 1; 
        beta = 0;
        a = 8'd20;  //Should not be in R5
        b = 8'd3;
        c = 18'd50; //Accumulated summ
        #2;
        $display("  Input: a=%0d (ignored), b=%0d, c=%0d | α=%b, β=%b", a, b, c, alpha, beta);

        //Cyclical B, new A is loaded. t = (0,1)
        $display("\n3. Cyclical B, new A is loaded. t = (0,1)");
        alpha = 0; 
        beta = 1;
        a = 8'd7;
        b = 8'd0;  //Ignored, taking old
        c = 18'd100;
        #2;
        $display("  Input: a=%0d, b=%0d (Ignored), c=%0d | α=%b, β=%b", a, b, c, alpha, beta);

        //Cyclical B + old A, t = (0,0)
        $display("\n[Тест 4] Режим (α,β)=(0,0) — полное переиспользование");
        alpha = 0; 
        beta = 0;
        a = 8'd99;  // Ignored
        b = 8'd99;  // Ignored
        c = 18'd200;
        #2;
        $display("  Input: a=%0d, b=%0d (Ignored), c=%0d | α=%b, β=%b", a, b, c, alpha, beta);


        #40;
        $display("\nFinished!");
        $finish;
    end

    //initial begin
    //    $dumpfile("tb_pe_waveform.vcd");
    //    $dumpvars();
    //end

endmodule

tb_pe_waveform.vcd
$date
	Mon Jun  1 11:49:59 2026
$end
$version
	Icarus Verilog
$end
$timescale
	1ps
$end
$scope module tb_pe $end
$var wire 17 ! c_j1 [16:0] $end
$var wire 1 " beta_j1 $end
$var wire 8 # b_j2 [7:0] $end
$var wire 1 $ alpha_j1 $end
$var wire 8 % a_j2 [7:0] $end
$var parameter 65 & ACC_WIDTH $end
$var parameter 32 ' ID $end
$var parameter 32 ( MODE $end
$var parameter 32 ) N $end
$var parameter 32 * WIDTH $end
$var reg 8 + a [7:0] $end
$var reg 1 , alpha $end
$var reg 8 - b [7:0] $end
$var reg 1 . beta $end
$var reg 17 / c [16:0] $end
$var reg 1 0 clk $end
$var reg 1 1 reset $end
$scope module pe $end
$var wire 8 2 a [7:0] $end
$var wire 1 , alpha $end
$var wire 8 3 b [7:0] $end
$var wire 1 . beta $end
$var wire 17 4 c [16:0] $end
$var wire 1 0 clk $end
$var wire 1 1 reset $end
$var wire 8 5 reg5_mult [7:0] $end
$var wire 8 6 reg2_1_out [7:0] $end
$var wire 17 7 r6_sum [16:0] $end
$var wire 8 8 r2_and2 [7:0] $end
$var wire 8 9 or1_r2 [7:0] $end
$var wire 1 : not1_and2 $end
$var wire 16 ; mult_to_sum [15:0] $end
$var wire 17 < c_j1 [16:0] $end
$var wire 1 " beta_j1 $end
$var wire 8 = b_j2 [7:0] $end
$var wire 8 > and2_or1 [7:0] $end
$var wire 8 ? and1_or1 [7:0] $end
$var wire 1 $ alpha_j1 $end
$var wire 8 @ a_j2 [7:0] $end
$var parameter 65 A ACC_WIDTH $end
$var parameter 32 B ID $end
$var parameter 32 C MODE $end
$var parameter 32 D N $end
$var parameter 33 E N1 $end
$var parameter 32 F WIDTH $end
$scope module and1 $end
$var wire 8 G in [7:0] $end
$var wire 1 , pass $end
$var wire 8 H out [7:0] $end
$var parameter 32 I WIDTH $end
$upscope $end
$scope module and2 $end
$var wire 1 : pass $end
$var wire 8 J out [7:0] $end
$var wire 8 K in [7:0] $end
$var parameter 32 L WIDTH $end
$upscope $end
$scope module d1 $end
$var wire 1 0 clk $end
$var wire 1 , d_in $end
$var wire 1 1 reset $end
$var reg 1 $ q_out $end
$upscope $end
$scope module d2 $end
$var wire 1 0 clk $end
$var wire 1 . d_in $end
$var wire 1 1 reset $end
$var reg 1 " q_out $end
$upscope $end
$scope module m1 $end
$var wire 16 M out [15:0] $end
$var wire 8 N in_y [7:0] $end
$var wire 8 O in_x [7:0] $end
$var parameter 32 P MODE $end
$var parameter 32 Q WIDTH $end
$scope begin genblk1 $end
$upscope $end
$upscope $end
$scope module n1 $end
$var wire 1 , a $end
$var wire 1 : out $end
$upscope $end
$scope module or1 $end
$var wire 8 R in_x [7:0] $end
$var wire 8 S in_y [7:0] $end
$var wire 8 T out [7:0] $end
$var parameter 32 U WIDTH $end
$upscope $end
$scope module r1 $end
$var wire 1 0 clk $end
$var wire 8 V d_in [7:0] $end
$var wire 8 W q_out [7:0] $end
$var wire 1 1 reset $end
$var parameter 33 X N $end
$var parameter 32 Y WIDTH $end
$scope begin gen_reg[0] $end
$var parameter 2 Z i $end
$scope module u_reg $end
$var wire 1 0 clk $end
$var wire 8 [ d_in [7:0] $end
$var wire 1 1 reset $end
$var parameter 32 \ WIDTH $end
$var reg 8 ] q_out [7:0] $end
$upscope $end
$upscope $end
$scope begin gen_reg[1] $end
$var parameter 2 ^ i $end
$scope module u_reg $end
$var wire 1 0 clk $end
$var wire 8 _ d_in [7:0] $end
$var wire 1 1 reset $end
$var parameter 32 ` WIDTH $end
$var reg 8 a q_out [7:0] $end
$upscope $end
$upscope $end
$scope begin gen_reg[2] $end
$var parameter 3 b i $end
$scope module u_reg $end
$var wire 1 0 clk $end
$var wire 8 c d_in [7:0] $end
$var wire 1 1 reset $end
$var parameter 32 d WIDTH $end
$var reg 8 e q_out [7:0] $end
$upscope $end
$upscope $end
$upscope $end
$scope module r2 $end
$var wire 1 0 clk $end
$var wire 8 f q_out [7:0] $end
$var wire 1 1 reset $end
$var wire 8 g d_in [7:0] $end
$var parameter 33 h N $end
$var parameter 32 i WIDTH $end
$scope begin gen_reg[0] $end
$var parameter 2 j i $end
$scope module u_reg $end
$var wire 1 0 clk $end
$var wire 8 k d_in [7:0] $end
$var wire 1 1 reset $end
$var parameter 32 l WIDTH $end
$var reg 8 m q_out [7:0] $end
$upscope $end
$upscope $end
$upscope $end
$scope module r2_1 $end
$var wire 1 0 clk $end
$var wire 8 n d_in [7:0] $end
$var wire 1 1 reset $end
$var parameter 32 o WIDTH $end
$var reg 8 p q_out [7:0] $end
$upscope $end
$scope module r34 $end
$var wire 1 0 clk $end
$var wire 8 q d_in [7:0] $end
$var wire 8 r q_out [7:0] $end
$var wire 1 1 reset $end
$var parameter 32 s N $end
$var parameter 32 t WIDTH $end
$scope begin gen_reg[0] $end
$var parameter 2 u i $end
$scope module u_reg $end
$var wire 1 0 clk $end
$var wire 8 v d_in [7:0] $end
$var wire 1 1 reset $end
$var parameter 32 w WIDTH $end
$var reg 8 x q_out [7:0] $end
$upscope $end
$upscope $end
$scope begin gen_reg[1] $end
$var parameter 2 y i $end
$scope module u_reg $end
$var wire 1 0 clk $end
$var wire 8 z d_in [7:0] $end
$var wire 1 1 reset $end
$var parameter 32 { WIDTH $end
$var reg 8 | q_out [7:0] $end
$upscope $end
$upscope $end
$upscope $end
$scope module r5 $end
$var wire 1 0 clk $end
$var wire 8 } d_in [7:0] $end
$var wire 1 . enable $end
$var wire 1 1 reset $end
$var parameter 32 ~ WIDTH $end
$var reg 8 !" q_out [7:0] $end
$upscope $end
$scope module r6 $end
$var wire 1 0 clk $end
$var wire 17 "" d_in [16:0] $end
$var parameter 65 #" ACC_WIDTH $end
$var parameter 32 $" N $end
$var parameter 32 %" WIDTH $end
$var reg 17 &" q_out [16:0] $end
$upscope $end
$scope module s1 $end
$var wire 17 '" in_accum [16:0] $end
$var wire 16 (" in_x [15:0] $end
$var wire 17 )" out [16:0] $end
$var wire 17 *" in_y [16:0] $end
$var parameter 65 +" ACC_WIDTH $end
$var parameter 32 ," MODE $end
$var parameter 32 -" N $end
$var parameter 32 ." WIDTH $end
$scope begin genblk1 $end
$upscope $end
$upscope $end
$upscope $end
$scope begin $ivl_for_loop0 $end
$var integer 32 /" i [31:0] $end
$upscope $end
$upscope $end
$enddefinitions $end
$comment Show the parameter values. $end
$dumpall
b1000 ."
b10 -"
b0 ,"
b10001 +"
b1000 %"
b10 $"
b10001 #"
b1000 ~
b1000 {
b1 y
b1000 w
b0 u
b1000 t
b10 s
b1000 o
b1000 l
b0 j
b1000 i
b1 h
b1000 d
b10 b
b1000 `
b1 ^
b1000 \
b0 Z
b1000 Y
b11 X
b1000 U
b1000 Q
b0 P
b1000 L
b1000 I
b1000 F
b11 E
b10 D
b0 C
b0 B
b10001 A
b1000 *
b10 )
b0 (
b0 '
b10001 &
$end
#0
$dumpvars
bx /"
bx *"
bx )"
b0 ("
bx '"
bx &"
bx ""
b0 !"
bx }
b0 |
b0 z
b0 x
bx v
b0 r
bx q
b0 p
bx n
b0 m
b0 k
b0 g
b0 f
b0 e
b0 c
b0 a
b0 _
b0 ]
bx [
b0 W
bx V
bx T
b0 S
bx R
b0 O
b0 N
b0 M
b0 K
b0 J
bx H
bx G
b0 @
bx ?
b0 >
b0 =
bx <
b0 ;
x:
bx 9
b0 8
bx 7
b0 6
b0 5
bx 4
bx 3
bx 2
11
00
bx /
x.
bx -
x,
bx +
b0 %
0$
b0 #
0"
bx !
$end
#1000
10
#2000
00
#3000
10
#4000
00
#5000
10
#6000
00
#7000
10
#8000
00
#9000
10
#10000
00
#11000
10
#12000
00
#13000
10
#14000
00
#15000
10
#16000
00
#17000
10
#18000
00
#19000
10
#20000
00
01
#21000
bx ;
bx M
bx ("
x"
x$
bx x
bx z
bx k
bx 6
bx N
bx g
bx p
bx ]
bx _
10
#22000
00
#23000
bx >
bx J
bx S
bx a
bx c
bx 8
bx K
bx f
bx m
bx %
bx @
bx r
bx |
10
#24000
00
#25000
bx #
bx =
bx W
bx e
10
#26000
00
#27000
10
#28000
00
#29000
10
#30000
b0 ?
b0 H
b0 R
1:
00
b0 /"
b0 /
b0 4
b0 ""
b0 [
b0 -
b0 3
b0 G
b0 V
b0 v
b0 +
b0 2
b0 q
b0 }
0.
0,
#31000
b0 *"
b0 ]
b0 _
b0 x
b0 z
0$
0"
b0 7
b0 &"
b0 '"
10
#32000
00
#33000
b0 %
b0 @
b0 r
b0 |
b0 a
b0 c
10
#34000
00
#35000
b0 #
b0 =
b0 W
b0 e
10
#36000
00
#37000
10
#38000
00
#39000
10
#40000
00
b1 /"
#41000
10
#42000
00
#43000
10
#44000
00
#45000
10
#46000
00
#47000
10
#48000
00
#49000
10
#50000
00
b10 /"
#51000
10
#52000
00
#53000
10
#54000
00
#55000
10
#56000
00
#57000
10
#58000
00
#59000
10
#60000
00
b11 /"
#61000
10
#62000
00
#63000
10
#64000
00
#65000
10
#66000
00
#67000
10
#68000
00
#69000
10
#70000
00
b100 /"
#71000
10
#72000
00
#73000
10
#74000
00
#75000
10
#76000
00
#77000
10
#78000
00
#79000
10
#80000
00
b101 /"
#81000
10
#82000
00
#83000
10
#84000
00
#85000
10
#86000
00
#87000
10
#88000
00
#89000
10
#90000
00
b110 /"
#91000
10
#92000
00
#93000
10
#94000
00
#95000
10
#96000
00
#97000
10
#98000
00
#99000
10
#100000
00
b111 /"
#101000
10
#102000
00
#103000
10
#104000
00
#105000
10
#106000
00
#107000
10
#108000
00
#109000
10
#110000
00
b1000 /"
#111000
10
#112000
00
#113000
10
#114000
00
#115000
10
#116000
00
#117000
10
#118000
00
#119000
10
#120000
00
b1001 /"
#121000
10
#122000
00
#123000
10
#124000
00
#125000
10
#126000
00
#127000
10
#128000
00
#129000
10
#130000
00
b1010 /"
#131000
10
#132000
00
#133000
10
#134000
00
#135000
b101 ]
b101 _
b1010 x
b1010 z
b1010 5
b1010 O
b1010 !"
1$
1"
b101 9
b101 T
b101 n
b0 >
b0 J
b0 S
b101 ?
b101 H
b101 R
0:
10
b101 [
b101 -
b101 3
b101 G
b101 V
b1010 v
b1010 +
b1010 2
b1010 q
b1010 }
1.
1,
#136000
00
#137000
b110010 !
b110010 <
b110010 )"
b110010 ;
b110010 M
b110010 ("
b1010 %
b1010 @
b1010 r
b1010 |
b101 k
b101 6
b101 N
b101 g
b101 p
b101 a
b101 c
10
#138000
00
#139000
b1100100 !
b1100100 <
b1100100 )"
b110010 *"
b11 ]
b11 _
b101 #
b101 =
b101 W
b101 e
b101 8
b101 K
b101 f
b101 m
b10100 x
b10100 z
0"
b110010 7
b110010 &"
b110010 '"
b11 9
b11 T
b11 n
b11 ?
b11 H
b11 R
10
b110010 /
b110010 4
b110010 ""
b11 [
b11 -
b11 3
b11 G
b11 V
b10100 v
b10100 +
b10100 2
b10100 q
b10100 }
0.
#140000
00
#141000
b1010000 !
b1010000 <
b1010000 )"
b11110 ;
b11110 M
b11110 ("
b10100 %
b10100 @
b10100 r
b10100 |
b11 k
b11 6
b11 N
b11 g
b11 p
b11 a
b11 c
10
#142000
00
#143000
b1111001 !
b1111001 <
b1111001 )"
b1100100 *"
b10101 ;
b10101 M
b10101 ("
b0 ]
b0 _
b11 #
b11 =
b11 W
b11 e
b11 8
b11 K
b11 f
b11 m
b111 x
b111 z
b111 5
b111 O
b111 !"
0$
1"
b1100100 7
b1100100 &"
b1100100 '"
b11 9
b11 T
b11 n
b11 >
b11 J
b11 S
b0 ?
b0 H
b0 R
1:
10
b1100100 /
b1100100 4
b1100100 ""
b0 [
b0 -
b0 3
b0 G
b0 V
b111 v
b111 +
b111 2
b111 q
b111 }
1.
0,
#144000
00
#145000
b111 %
b111 @
b111 r
b111 |
b0 a
b0 c
10
#146000
00
#147000
b11011101 !
b11011101 <
b11011101 )"
b11001000 *"
b1100011 ]
b1100011 _
b0 #
b0 =
b0 W
b0 e
b1100011 x
b1100011 z
0"
b11001000 7
b11001000 &"
b11001000 '"
10
b11001000 /
b11001000 4
b11001000 ""
b1100011 [
b1100011 -
b1100011 3
b1100011 G
b1100011 V
b1100011 v
b1100011 +
b1100011 2
b1100011 q
b1100011 }
0.
#148000
00
#149000
b1100011 %
b1100011 @
b1100011 r
b1100011 |
b1100011 a
b1100011 c
10
#150000
00
#151000
b1100011 #
b1100011 =
b1100011 W
b1100011 e
10
